modular_search/__init__.py
modular_search/llm.py
modular_search/py.typed
modular_search/scraper.py
modular_search/blocks/__init__.py
modular_search/blocks/codebase.py
modular_search/blocks/core.py
modular_search/controllers/__init__.py
modular_search/controllers/codebase.py
modular_search/controllers/core.py
modular_search/engines/__init__.py
modular_search/engines/core.py
modular_search/engines/deep_google.py
modular_search/engines/google.py
modular_search/extractors/__init__.py
modular_search/extractors/codebase.py
modular_search/extractors/core.py
modular_search/rerankers/__init__.py
modular_search/rerankers/codebase.py
modular_search/rerankers/core.py
modular_search-0.1.7.dist-info/METADATA
modular_search-0.1.7.dist-info/WHEEL
modular_search-0.1.7.dist-info/licenses/LICENSE
modular_search-0.1.7.dist-info/RECORD
