Metadata-Version: 2.4
Name: modular-search
Version: 0.1.7
Summary: A Modular Search Framework for Military Developers
Author-email: Prannaya Gupta <prannayagupta@gmail.com>
License-File: LICENSE
Requires-Python: >=3.9
Requires-Dist: beautifulsoup4>=4.13.4
Requires-Dist: googlesearch-python>=1.3.0
Requires-Dist: pydantic>=2.11.5
Requires-Dist: requests>=2.32.3
Requires-Dist: scikit-learn>=1.6.1
